azure/mgmt/signalr/__init__.py
azure/mgmt/signalr/_configuration.py
azure/mgmt/signalr/_patch.py
azure/mgmt/signalr/_serialization.py
azure/mgmt/signalr/_signal_rmanagement_client.py
azure/mgmt/signalr/_vendor.py
azure/mgmt/signalr/_version.py
azure/mgmt/signalr/py.typed
azure/mgmt/signalr/aio/__init__.py
azure/mgmt/signalr/aio/_configuration.py
azure/mgmt/signalr/aio/_patch.py
azure/mgmt/signalr/aio/_signal_rmanagement_client.py
azure/mgmt/signalr/aio/operations/__init__.py
azure/mgmt/signalr/aio/operations/_operations.py
azure/mgmt/signalr/aio/operations/_patch.py
azure/mgmt/signalr/aio/operations/_signal_r_operations.py
azure/mgmt/signalr/aio/operations/_signal_rcustom_certificates_operations.py
azure/mgmt/signalr/aio/operations/_signal_rcustom_domains_operations.py
azure/mgmt/signalr/aio/operations/_signal_rprivate_endpoint_connections_operations.py
azure/mgmt/signalr/aio/operations/_signal_rprivate_link_resources_operations.py
azure/mgmt/signalr/aio/operations/_signal_rshared_private_link_resources_operations.py
azure/mgmt/signalr/aio/operations/_usages_operations.py
azure/mgmt/signalr/models/__init__.py
azure/mgmt/signalr/models/_models_py3.py
azure/mgmt/signalr/models/_patch.py
azure/mgmt/signalr/models/_signal_rmanagement_client_enums.py
azure/mgmt/signalr/operations/__init__.py
azure/mgmt/signalr/operations/_operations.py
azure/mgmt/signalr/operations/_patch.py
azure/mgmt/signalr/operations/_signal_r_operations.py
azure/mgmt/signalr/operations/_signal_rcustom_certificates_operations.py
azure/mgmt/signalr/operations/_signal_rcustom_domains_operations.py
azure/mgmt/signalr/operations/_signal_rprivate_endpoint_connections_operations.py
azure/mgmt/signalr/operations/_signal_rprivate_link_resources_operations.py
azure/mgmt/signalr/operations/_signal_rshared_private_link_resources_operations.py
azure/mgmt/signalr/operations/_usages_operations.py
azure_mgmt_signalr-1.2.0.dist-info/LICENSE
azure_mgmt_signalr-1.2.0.dist-info/METADATA
azure_mgmt_signalr-1.2.0.dist-info/WHEEL
azure_mgmt_signalr-1.2.0.dist-info/top_level.txt
azure_mgmt_signalr-1.2.0.dist-info/RECORD
